discordme/__init__.py
discordme/discord_api.py
discordme/utils.py
discordme-0.3.0.dist-info/METADATA
discordme-0.3.0.dist-info/WHEEL
discordme-0.3.0.dist-info/top_level.txt
discordme-0.3.0.dist-info/RECORD
